pluralru/pluralru.py
pluralru-1.1.dist-info/LICENSE
pluralru-1.1.dist-info/METADATA
pluralru-1.1.dist-info/WHEEL
pluralru-1.1.dist-info/top_level.txt
pluralru-1.1.dist-info/RECORD
