Metadata-Version: 2.1
Name: pluralru
Version: 1.1
Summary: Возвращает строку с множественным числом
Home-page: UNKNOWN
Author: Blazzerrr
License: MIT
Platform: UNKNOWN
Classifier: License :: OSI Approved :: MIT License
Classifier: Programming Language :: Python :: 3
Classifier: Programming Language :: Python :: 3.7
